pytest_prairielearn_grader/__init__.py
pytest_prairielearn_grader/_student_code_runner.py
pytest_prairielearn_grader/fixture.py
pytest_prairielearn_grader/json_utils.py
pytest_prairielearn_grader/plugin.py
pytest_prairielearn_grader/py.typed
pytest_prairielearn_grader/utils.py
pytest_prairielearn_grader-0.2.2.dist-info/METADATA
pytest_prairielearn_grader-0.2.2.dist-info/WHEEL
pytest_prairielearn_grader-0.2.2.dist-info/entry_points.txt
pytest_prairielearn_grader-0.2.2.dist-info/licenses/LICENSE
pytest_prairielearn_grader-0.2.2.dist-info/RECORD
