Metadata-Version: 2.4
Name: pytest-prairielearn-grader
Version: 0.2.2
Summary: A pytest plugin for autograding Python code. Designed for use with the PrairieLearn platform.
Project-URL: repository, https://github.com/eliotwrobson/pl-python-autograder-v2
Author-email: Eliot Robson <eliot.robson24@gmail.com>
License: MIT License
License-File: LICENSE
Classifier: Development Status :: 3 - Alpha
Classifier: License :: OSI Approved :: MIT License
Classifier: Programming Language :: Python :: 3.11
Classifier: Programming Language :: Python :: 3.12
Classifier: Programming Language :: Python :: 3.13
Classifier: Programming Language :: Python :: 3.14
Requires-Python: >=3.11
Requires-Dist: dill>=0.4.0
Requires-Dist: prettytable>=3.8.0
Requires-Dist: pytest
